<item>
    <title>Return to Never Land</title>
    <meta>
        <imdb>tt0280030</imdb>
        <content>movie</content>
        <title>Return to Never Land</title>
        <year>2002</year>
    </meta>
    <link>https://uptostream.com/te8juq9sjwia</link>
    <thumbnail>https://image.tmdb.org/t/p/w1280/b5IyizEBveh2ZE2SEo9O4sJ4CHi.jpg</thumbnail>
    <fanart>https://image.tmdb.org/t/p/w1280/5EZ5qVC5yRIEmdEKuRSDjjhW1Cp.jpg</fanart>
</item>
<item>
    <title>Lilo & Stitch</title>
    <meta>
        <imdb>tt0275847</imdb>
        <content>movie</content>
        <title>Lilo & Stitch</title>
        <year>2002</year>
    </meta>
    <link>https://uptostream.com/i6q8oxi2zxbl</link>
    <thumbnail>https://image.tmdb.org/t/p/w1280/tVaEulzowKhMhDvHNNYb9rNEZPB.jpg</thumbnail>
    <fanart>https://image.tmdb.org/t/p/w1280/gFx6arXVp69XwH2m2cy3QemV9Nh.jpg</fanart>
</item>
<item>
    <title>The Tigger Movie</title>
    <meta>
        <imdb>tt0220099</imdb>
        <content>movie</content>
        <title>The Tigger Movie</title>
        <year>2000</year>
    </meta>
    <link>https://uptostream.com/h2srl5lodzh7</link>
    <thumbnail>https://image.tmdb.org/t/p/w1280/lxuiGvLHIL1ZyePP7bn6FcKj0Mr.jpg</thumbnail>
    <fanart>https://image.tmdb.org/t/p/w1280/3t9LrLWtT6AAGCpP95mmmWw1z3D.jpg</fanart>
</item>
<item>
    <title>Princess and the Frog</title>
    <meta>
        <content>movie</content>
        <imdb>tt0780521</imdb>
        <title>Princess in the Frog</title>
        <year>2009</year>
    </meta>
    <link>https://uptostream.com/lgtqr27utbny</link>
    <thumbnail>https://image.tmdb.org/t/p/w1280/bVRHirC6uIZL9VtRqYRxdedYnOG.jpg</thumbnail>
    <fanart>https://image.tmdb.org/t/p/w700_and_h392_bestv2/wC5xdlg6WceCWUXQzS3pIwTfkEJ.jpg</fanart>
</item>
<item>
    <title>Mickey's House of Villains</title>
    <meta>
        <imdb>tt0329374</imdb>
        <content>movie</content>
        <title>Mickey's House of Villains</title>
        <year>2001</year>
    </meta>
    <link>https://uptostream.com/et1ebls1ljgx</link>
    <thumbnail>https://image.tmdb.org/t/p/w1280/lE6eJ1TrOzlRMUgjonSRQRWk3l3.jpg</thumbnail>
    <fanart>https://image.tmdb.org/t/p/w1000_and_h563_face/ozrtVyozRLBT4fg3GQnI6QP6HeQ.jpg</fanart>
</item>
<item>
    <title>Ponyo</title>
    <meta>
        <imdb>tt0876563</imdb>
        <content>movie</content>
        <title>Ponyo</title>
        <year>2008</year>
    </meta>
    <link>https://uptostream.com/n4u3u3j5rx7y</link>
    <thumbnail>https://image.tmdb.org/t/p/w1280/3s0mpSpLkI7cIhqWGrGbsiyvlsH.jpg</thumbnail>
    <fanart>https://image.tmdb.org/t/p/w1280/vK86ykZTcyMjYkin1zWfTulbU34.jpg</fanart>
</item>
<item>
    <title>Tinker Bell</title>
    <meta>
        <imdb>tt0823671</imdb>
        <content>movie</content>
        <title>Tinker Bell</title>
        <year>2008</year>
    </meta>
    <link>https://uptostream.com/w1qp6yak4vm4</link>
    <thumbnail>https://image.tmdb.org/t/p/w1280/dx9FiWtcY4u5Kla6Cetw1a6W2qK.jpg</thumbnail>
    <fanart>https://image.tmdb.org/t/p/w1280/j7r0HwdQibJYPxmStqqucqWaX7u.jpg</fanart>
</item>
<item>
    <title>Tinker Bell and the Lost Treasure</title>
    <meta>
        <imdb>tt1216516</imdb>
        <content>movie</content>
        <title>Tinker Bell and the Lost Treasure</title>
        <year>2009</year>
    </meta>
    <link>https://uptostream.com/8nv48319l7fu</link>
    <thumbnail>https://image.tmdb.org/t/p/w1280/c695u6KN4E42DMbzzvq3UHLI47S.jpg</thumbnail>
    <fanart>https://image.tmdb.org/t/p/w1280/fNzWr09uCmRSIPBxPNHa2r8pasZ.jpg</fanart>
</item>
<item>
    <title>My Friends Tigger & Pooh's Friendly Tails</title>
    <meta>
        <imdb>tt1204933</imdb>
        <content>movie</content>
        <title>My Friends Tigger & Pooh's Friendly Tails</title>
        <year>2008</year>
    </meta>
    <link>https://uptostream.com/ijlbvvxhl93w</link>
    <thumbnail>https://image.tmdb.org/t/p/w1280/sy18W9WWN8ZT5nyU11svBAcYhCb.jpg</thumbnail>
    <fanart>https://image.tmdb.org/t/p/w1280/raMcSQbfTb2sQcLqbArSD0RyK7q.jpg</fanart>
</item>
<item>
    <title>Kim Possible: A Sitch in Time</title>
    <meta>
        <imdb>tt0389074</imdb>
        <content>movie</content>
        <title>Kim Possible: A Sitch in Time</title>
        <year>2003</year>
    </meta>
    <link>https://uptostream.com/zjx0wll3kfme</link>
    <thumbnail>https://image.tmdb.org/t/p/w1280/817PTtqvxBGLuRlGqgnyXY9NVj3.jpg</thumbnail>
    <fanart>https://image.tmdb.org/t/p/w1280/eTn3ytdldn5umugAxam2wp3jqWN.jpg</fanart>
</item>
<item>
    <title>A Christmas Carol</title>
    <meta>
        <imdb>tt1067106</imdb>
        <content>movie</content>
        <title>A Christmas Carol</title>
        <year>2009</year>
    </meta>
    <link>https://uptostream.com/eajyxn2m10ff</link>
    <thumbnail>https://image.tmdb.org/t/p/w1280/jeOCcjUAcSYleVwhsaKEPT4CYwF.jpg</thumbnail>
    <fanart>https://image.tmdb.org/t/p/w1280/GtwSStViUdhKGf0d7tCkR7alKV.jpg</fanart>
</item>
<item>
    <title>An Extremely Goofy Movie</title>
    <meta>
        <imdb>tt0208185</imdb>
        <content>movie</content>
        <title>An Extremely Goofy Movie</title>
        <year>2000</year>
    </meta>
    <link>https://uptostream.com/zoaum8vc3c5h</link>
    <thumbnail>https://image.tmdb.org/t/p/w1280/kHV9ABnZtDeDtSQfTNIveSoxS9m.jpg</thumbnail>
    <fanart>https://image.tmdb.org/t/p/w1280/nxhsdq7g8FzuFUG218q0CrUsqVq.jpg</fanart>
</item>
<item>
    <title>Tarzan II</title>
    <meta>
        <imdb>tt0437503</imdb>
        <content>movie</content>
        <title>Tarzan II</title>
        <year>2005</year>
    </meta>
    <link>https://uptostream.com/uunyfpsib363</link>
    <thumbnail>https://image.tmdb.org/t/p/w1280/4PMZm53uFvq1eSgNbosr9xJTCM1.jpg</thumbnail>
    <fanart>https://image.tmdb.org/t/p/w1280/mhleoBTypRbM9FivAJg1YiNFc7j.jpg</fanart>
</item>
<item>
    <title>Spirited Away</title>
    <meta>
        <imdb>tt0245429</imdb>
        <content>movie</content>
        <title>Spirited Away</title>
        <year>2001</year>
    </meta>
    <link>https://uptostream.com/hoympnre30bu</link>
    <thumbnail>https://image.tmdb.org/t/p/w1280/oRvMaJOmapypFUcQqpgHMZA6qL9.jpg</thumbnail>
    <fanart>https://image.tmdb.org/t/p/w1280/mnpRKVSXBX6jb56nabvmGKA0Wig.jpg</fanart>
</item>
<item>
    <title>Enchanted</title>
    <meta>
        <imdb>tt0461770</imdb>
        <content>movie</content>
        <title>Enchanted</title>
        <year>2007</year>
    </meta>
    <link>https://uptostream.com/1e7qr2a2hl0w</link>
    <thumbnail>https://image.tmdb.org/t/p/w1280/65EfHNQ6NCeAoRPNLRhTyLqNZmU.jpg</thumbnail>
    <fanart>https://image.tmdb.org/t/p/w1280/9l5Nzo1qbEslfCu2NYWimpZ1Vkc.jpg</fanart>
</item>
<item>
    <title>Meet the Robinsons</title>
    <meta>
        <imdb>tt0396555</imdb>
        <content>movie</content>
        <title>Meet the Robinsons</title>
        <year>2007</year>
    </meta>
    <link>https://uptostream.com/t1ep2uvmujxh</link>
    <thumbnail>https://image.tmdb.org/t/p/w1280/oe7w9SxGmpSW1dlz5QaVVKWBEVz.jpg</thumbnail>
    <fanart>https://image.tmdb.org/t/p/w1280/jxWA2lDLidicmmDymnxlz53zAb9.jpg</fanart>
</item>
<item>
    <title>Atlantis: The Lost Empire</title>
    <meta>
        <imdb>tt0230011</imdb>
        <content>movie</content>
        <title>Atlantis: The Lost Empire</title>
        <year>2001</year>
    </meta>
    <link>https://uptostream.com/xfjcot9c0mbz</link>
    <thumbnail>https://image.tmdb.org/t/p/w1280/9kbLIQEj99g5Hb9g1IG3VNdtt3h.jpg</thumbnail>
    <fanart>https://image.tmdb.org/t/p/w1280/fYr0fqT9NImOuaN1QgnDHgGh4Ci.jpg</fanart>
</item>
<item>
    <title>The Emperor's New Groove</title>
    <meta>
        <imdb>tt0120917</imdb>
        <content>movie</content>
        <title>The Emperor's New Groove</title>
        <year>2000</year>
    </meta>
    <link>https://uptostream.com/ihkhwqbypy73</link>
    <thumbnail>https://image.tmdb.org/t/p/w1280/6c4dzX5Io2i9tP30ZRnrhwjsYt7.jpg</thumbnail>
    <fanart>https://image.tmdb.org/t/p/w1280/wWzZUuvl17RU7rlPwTsG5y1wgxi.jpg</fanart>
</item>
<item>
    <title>101 Dalmatians II: Patch's London Adventure</title>
    <meta>
        <imdb>tt0324941</imdb>
        <content>movie</content>
        <title>101 Dalmatians II: Patch's London Adventure</title>
        <year>2003</year>
    </meta>
    <link>https://uptostream.com/e0sjaarhj31p</link>
    <thumbnail>https://image.tmdb.org/t/p/w1280/ht4h6I7WwaZa1E8xzb1jE94mDvS.jpg</thumbnail>
    <fanart>https://image.tmdb.org/t/p/w1280/kFkFiDdTGv1eb5C0P44KFUGstBA.jpg</fanart>
</item>
<item>
    <title>The Little Mermaid: Ariel's Beginning</title>
    <meta>
        <imdb>tt0969647</imdb>
        <content>movie</content>
        <title>The Little Mermaid: Ariel's Beginning</title>
        <year>2008</year>
    </meta>
    <link>https://uptostream.com/x28i0ztnii0a</link>
    <thumbnail>https://image.tmdb.org/t/p/w1280/mBnN8so6MG0q0i2TqtPgravPOZe.jpg</thumbnail>
    <fanart>https://image.tmdb.org/t/p/w1280/2Er8UNtyFhZWRrOoVaWQ2QuuVq3.jpg</fanart>
</item>
<item>
    <title>Pooh's Heffalump Movie</title>
    <meta>
        <imdb>tt0407121</imdb>
        <content>movie</content>
        <title>Pooh's Heffalump Movie</title>
        <year>2005</year>
    </meta>
    <link>https://uptostream.com/ktkzxnjwelou</link>
    <thumbnail>https://image.tmdb.org/t/p/w1280/ow61dkcJcfVFW2n7YpUVsMzcpk5.jpg</thumbnail>
    <fanart>https://image.tmdb.org/t/p/w1280/hzQ9VVlODgIDt6m9aQM2VoMtkcj.jpg</fanart>
</item>
<item>
    <title>Tarzan & Jane</title>
    <meta>
        <imdb>tt0313680</imdb>
        <content>movie</content>
        <title>Tarzan & Jane</title>
        <year>2002</year>
    </meta>
    <link>https://uptostream.com/gb6x7ic8zyz4</link>
    <thumbnail>https://image.tmdb.org/t/p/w1280/hy2Jul5g4LWr6pgMo3L2MPN3qsn.jpg</thumbnail>
    <fanart>https://image.tmdb.org/t/p/w1280/x2FeMuxOL6vZt7VY8XlGWUniMcg.jpg</fanart>
</item>
<item>
    <title>Piglet's Big Movie</title>
    <meta>
        <imdb>tt0323642</imdb>
        <content>movie</content>
        <title>Piglet's Big Movie</title>
        <year>2003</year>
    </meta>
    <link>https://uptostream.com/g3mmatw8yfw9</link>
    <thumbnail>https://image.tmdb.org/t/p/w1280/gM4rWSXfPMeXorIKXNr5kuxLPkz.jpg</thumbnail>
    <fanart>https://image.tmdb.org/t/p/w1280/kJABbqsbe8jLQyDudjfiYBBSUvp.jpg</fanart>
</item>
<item>
    <title>Home on the Range</title>
    <meta>
        <imdb>tt0299172</imdb>
        <content>movie</content>
        <title>Home on the Range</title>
        <year>2004</year>
    </meta>
    <link>https://uptostream.com/yx84z9vvhpts</link>
    <thumbnail>https://image.tmdb.org/t/p/w1280/1KFa2Mzzn2DMlC95eJwRYgRsHI.jpg</thumbnail>
    <fanart>https://image.tmdb.org/t/p/w1280/rQKlcMY8i3elENXEHlkAbQr3xiG.jpg</fanart>
</item>
<item>
    <title>Winnie the Pooh: A Very Merry Pooh Year</title>
    <meta>
        <imdb>tt0324572</imdb>
        <content>movie</content>
        <title>Winnie the Pooh: A Very Merry Pooh Year</title>
        <year>2002</year>
    </meta>
    <link>https://uptostream.com/1s05oydtbh95</link>
    <thumbnail>https://image.tmdb.org/t/p/w1280/3xuM4G7fUecAXCgSxddht0rD9w1.jpg</thumbnail>
    <fanart>https://image.tmdb.org/t/p/w1280/bow7Bvllz9xBLk8iCgGwK96tH9m.jpg</fanart>
</item>
<item>
    <title>The Wild</title>
    <meta>
        <imdb>tt0405469</imdb>
        <content>movie</content>
        <title>The Wild</title>
        <year>2006</year>
    </meta>
    <link>https://uptostream.com/zcd55d5a7usi</link>
    <thumbnail>https://image.tmdb.org/t/p/w1280/uxTtgh4tpSWVulXLCDqKU10cWXo.jpg</thumbnail>
    <fanart>https://image.tmdb.org/t/p/w1280/z8bCwHtKypfDoqChf41pKWR41Xb.jpg</fanart>
</item>
<item>
    <title>The Fox and the Hound 2</title>
    <meta>
        <imdb>tt0465997</imdb>
        <content>movie</content>
        <title>The Fox and the Hound 2</title>
        <year>2006</year>
    </meta>
    <link>https://uptostream.com/slhmju1r49jl</link>
    <thumbnail>https://image.tmdb.org/t/p/w1280/2SK9VetMoTvMWxeSE8cZIlU4Ke7.jpg</thumbnail>
    <fanart>https://image.tmdb.org/t/p/w1280/fTdkljwRdpNR63xWly8aJ1ksMEx.jpg</fanart>
</item>
<item>
    <title>Chicken Little</title>
    <meta>
        <imdb>tt0371606</imdb>
        <content>movie</content>
        <title>Chicken Little</title>
        <year>2005</year>
    </meta>
    <link>https://uptostream.com/d7z39icl0duk</link>
    <thumbnail>https://image.tmdb.org/t/p/w1280/iLMALbInUmbNn1tHmxJEWm5MyjP.jpg</thumbnail>
    <fanart>https://image.tmdb.org/t/p/w1280/9YqNb9V9lded8ZDjMz8nkQLpq15.jpg</fanart>
</item>
<item>
    <title>Brother Bear</title>
    <meta>
        <imdb>tt0328880</imdb>
        <content>movie</content>
        <title>Brother Bear</title>
        <year>2003</year>
    </meta>
    <link>https://uptostream.com/rhfnm2my8isz</link>
    <thumbnail>https://image.tmdb.org/t/p/w1280/otptPbEY0vBostmo95xwiiumMJm.jpg</thumbnail>
    <fanart>https://image.tmdb.org/t/p/w1280/mDgZ8aLCrH4NcUJIvF0W5B8qa4G.jpg</fanart>
</item>
<item>
    <title>Brother Bear 2</title>
    <meta>
        <imdb>tt0465925</imdb>
        <content>movie</content>
        <title>Brother Bear 2</title>
        <year>2006</year>
    </meta>
    <link>https://uptostream.com/luyd04edg2b1</link>
    <thumbnail>https://image.tmdb.org/t/p/w1280/msZSTfilEF6hw47HTuf5AeXAO8R.jpg</thumbnail>
    <fanart>https://image.tmdb.org/t/p/w1280/zhMiJmPuX2o2bbXWWZNUgVbw3OM.jpg</fanart>
</item>
<item>
    <title>Atlantis: Milo's Return</title>
    <meta>
        <imdb>tt0344864</imdb>
        <content>movie</content>
        <title>Atlantis: Milo's Return</title>
        <year>2003</year>
    </meta>
    <link>https://uptostream.com/1u4nkbve5bs5</link>
    <thumbnail>https://image.tmdb.org/t/p/w1280/jnGcMr21vmgR82hjXOBLMgJx1hw.jpg</thumbnail>
    <fanart>https://image.tmdb.org/t/p/w1280/yPzmjdJnpG1Xy5V8GmJfqZHm0Cm.jpg</fanart>
</item>
<item>
    <title>Howl's Moving Castle</title>
    <meta>
        <imdb>tt0347149</imdb>
        <content>movie</content>
        <title>Howl's Moving Castle</title>
        <year>2004</year>
    </meta>
    <link>https://uptostream.com/prqp6dc3kgct</link>
    <thumbnail>https://image.tmdb.org/t/p/w1280/iMarB2ior30OAXjPa7QIdeyUfM1.jpg</thumbnail>
    <fanart>https://image.tmdb.org/t/p/w1280/cGyqa5PxiWSsG7NSw3ufCj0JW9k.jpg</fanart>
</item>
<item>
    <title>Dinosaur</title>
    <meta>
        <imdb>tt0130623</imdb>
        <content>movie</content>
        <title>Dinosaur</title>
        <year>2000</year>
    </meta>
    <link>https://uptostream.com/n3z2snyknybi</link>
    <thumbnail>https://image.tmdb.org/t/p/w1280/rSje3FS7ycJSglowlngjsvDt7vO.jpg</thumbnail>
    <fanart>https://image.tmdb.org/t/p/w1280/LT2796bodQIvIV50KcyrsIkq6r.jpg</fanart>
</item>
<item>
    <title>The Hunchback of Notre Dame II</title>
    <meta>
        <imdb>tt0257778</imdb>
        <content>movie</content>
        <title>The Hunchback of Notre Dame II</title>
        <year>2002</year>
    </meta>
    <link>https://uptostream.com/y70v4gg6z1o3</link>
    <thumbnail>https://image.tmdb.org/t/p/w1280/xgKY2n9uJ9iP7zSOBWt75FNvHnP.jpg</thumbnail>
    <fanart>https://image.tmdb.org/t/p/w1280/akciH4vlTbFtbzpL2R7zCEwmwZJ.jpg</fanart>
</item>
<item>
    <title>Treasure Planet</title>
    <meta>
        <imdb>tt0133240</imdb>
        <content>movie</content>
        <title>Treasure Planet</title>
        <year>2002</year>
    </meta>
    <link>https://uptostream.com/biimntb3is8q</link>
    <thumbnail>https://image.tmdb.org/t/p/w1280/yfcoA7q9n852yVnYa0VcAchgA72.jpg</thumbnail>
    <fanart>https://image.tmdb.org/t/p/w1280/hEwbDCvPBWMxfaP9cFImy7rZQtV.jpg</fanart>
</item>
<item>
    <title>Cinderella II: Dreams Come True</title>
    <meta>
        <imdb>tt0291082</imdb>
        <content>movie</content>
        <title>Cinderella II: Dreams Come True</title>
        <year>2002</year>
    </meta>
    <link>https://uptostream.com/eov848z3y5uq</link>
    <thumbnail>https://image.tmdb.org/t/p/w1280/gmyZ10NuMrQ5FZHXsqVpRQJ5JPy.jpg</thumbnail>
    <fanart>https://image.tmdb.org/t/p/w1280/4ErXZZgpXPxDcCLnnLXysK03ss9.jpg</fanart>
</item>
<item>
    <title>Winnie the Pooh: Springtime with Roo</title>
    <meta>
        <imdb>tt0384696</imdb>
        <content>movie</content>
        <title>Winnie the Pooh: Springtime with Roo</title>
        <year>2004</year>
    </meta>
    <link>https://uptostream.com/6kj0yr7gqzcg</link>
    <thumbnail>https://image.tmdb.org/t/p/w1280/8IJAOQHMLg1pUEg8rlLwhqN18mc.jpg</thumbnail>
    <fanart>https://image.tmdb.org/t/p/w1280/eg6db3KpXpUBfFaWQNa7S6Ob3MC.jpg</fanart>
</item>
<item>
    <title>Lady and the Tramp II: Scamp's Adventure</title>
    <meta>
        <imdb>tt0249677</imdb>
        <content>movie</content>
        <title>Lady and the Tramp II: Scamp's Adventure</title>
        <year>2001</year>
    </meta>
    <link>https://uptostream.com/lo1f6kemrihq</link>
    <thumbnail>https://image.tmdb.org/t/p/w1280/bc2yxExkW5tiJf8ASkgsEYHiluy.jpg</thumbnail>
    <fanart>https://image.tmdb.org/t/p/w1280/6nZP8g5HFGckLF4e933kvszKMxC.jpg</fanart>
</item>
<item>
    <title>Kim Possible: The Secret Files</title>
    <meta>
        <imdb>tt0380481</imdb>
        <content>movie</content>
        <title>Kim Possible: The Secret Files</title>
        <year>2003</year>
    </meta>
    <link>https://uptostream.com/8oevmhrppmfm</link>
    <thumbnail>https://image.tmdb.org/t/p/w1280/4smyLRVY7Lwx0d3pbPEAr9CYedx.jpg</thumbnail>
    <fanart>https://image.tmdb.org/t/p/w1280/gzkBXZKsPtoBsQjWVvQRFErgPpN.jpg</fanart>
</item>
<item>
    <title>The Little Mermaid II: Return to the Sea</title>
    <meta>
        <imdb>tt0240684</imdb>
        <content>movie</content>
        <title>The Little Mermaid II: Return to the Sea</title>
        <year>2000</year>
    </meta>
    <link>https://uptostream.com/wrq3g3wols3c</link>
    <thumbnail>https://image.tmdb.org/t/p/w1280/1P7zIGdv3Z0A5L6F30Qx0r69cmI.jpg</thumbnail>
    <fanart>https://image.tmdb.org/t/p/w1280/iDR0r2g9kzhyODUWwEyKgbc8szD.jpg</fanart>
</item>
<item>
    <title>Mulan II</title>
    <meta>
        <imdb>tt0279967</imdb>
        <content>movie</content>
        <title>Mulan II</title>
        <year>2004</year>
    </meta>
    <link>https://uptostream.com/bmohs1trlk57</link>
    <thumbnail>https://image.tmdb.org/t/p/w1280/ebuRP7g3tJlLxeejylu4Wx4Qsjv.jpg</thumbnail>
    <fanart>https://image.tmdb.org/t/p/w1280/7qzlrqvvXvl4SYbjTErZ0x8uZxA.jpg</fanart>
</item>
<item>
    <title>The Jungle Book 2</title>
    <meta>
        <imdb>tt0283426</imdb>
        <content>movie</content>
        <title>The Jungle Book 2</title>
        <year>2003</year>
    </meta>
    <link>https://uptostream.com/720e3j16b9la</link>
    <thumbnail>https://image.tmdb.org/t/p/w1280/q2GTnlj84EqUJGvqAQy6ib2JznI.jpg</thumbnail>
    <fanart>https://image.tmdb.org/t/p/w1280/tmPv63fkjFRVy0F7PFuuR3cJ5Xf.jpg</fanart>
</item>
<item>
    <title>Recess: School's Out</title>
    <meta>
        <imdb>tt0265632</imdb>
        <content>movie</content>
        <title>Recess: School's Out</title>
        <year>2001</year>
    </meta>
    <link>https://uptostream.com/z1jadpc9a19k</link>
    <thumbnail>https://image.tmdb.org/t/p/w1280/eclW5yA0X2A4F4qDlqJ354phBr1.jpg</thumbnail>
    <fanart>https://image.tmdb.org/t/p/w1280/fuRd2fUHbhj56xpyhGQ7HGP2Hil.jpg</fanart>
</item>
<item>
    <title>Kim Possible: The Villain Files</title>
    <meta>
        <imdb>tt1910568</imdb>
        <content>movie</content>
        <title>Kim Possible: The Villain Files</title>
        <year>2004</year>
    </meta>
    <link>https://uptostream.com/mdc60wk0l402</link>
    <thumbnail>https://image.tmdb.org/t/p/w1280/coTkGMmlzR06AnvplVTDmmXrOPf.jpg</thumbnail>
    <fanart>https://image.tmdb.org/t/p/w1280/zJ0BIrVHYAIJct1pWqUpm5utT4c.jpg</fanart>
</item>
<item>
    <title>Stitch! The Movie</title>
    <meta>
        <imdb>tt0348124</imdb>
        <content>movie</content>
        <title>Stitch! The Movie</title>
        <year>2003</year>
    </meta>
    <link>https://uptostream.com/5s4aekadx9pb</link>
    <thumbnail>https://image.tmdb.org/t/p/w1280/rRcURWfP7jFJrRLSpa9YN0eZ2Cc.jpg</thumbnail>
    <fanart>https://image.tmdb.org/t/p/w1280/6tgqVJmxndtbOu2bvxYtfFCd8Wi.jpg</fanart>
</item>
<item>
    <title>Lilo & Stitch 2: Stitch has a Glitch</title>
    <meta>
        <imdb>tt0457993</imdb>
        <content>movie</content>
        <title>Lilo & Stitch 2: Stitch has a Glitch</title>
        <year>2005</year>
    </meta>
    <link>https://uptostream.com/6wopc9tqyq0s</link>
    <thumbnail>https://image.tmdb.org/t/p/w1280/hUmQxcaWdHjwovD1ABrTHbpTcoo.jpg</thumbnail>
    <fanart>https://image.tmdb.org/t/p/w1280/2L6fv2dqDRS7LMLXN8w1UXZfy5O.jpg</fanart>
</item>
<item>
    <title>Kim Possible Movie: So the Drama</title>
    <meta>
        <imdb>tt0446724</imdb>
        <content>movie</content>
        <title>Kim Possible Movie: So the Drama</title>
        <year>2005</year>
    </meta>
    <link>https://uptostream.com/auejsitgj8uo</link>
    <thumbnail>https://image.tmdb.org/t/p/w1280/2VHoWyw70EhH3gGfm9b8ybu75MY.jpg</thumbnail>
    <fanart>https://image.tmdb.org/t/p/w1280/c93ErX1pV7VWwiPbWAhv3wKLYKD.jpg</fanart>
</item>
<item>
    <title>Mickey's Twice Upon a Christmas</title>
    <meta>
        <imdb>tt0424279</imdb>
        <content>movie</content>
        <title>Mickey's Twice Upon a Christmas</title>
        <year>2004</year>
    </meta>
    <link>https://uptostream.com/ycthrkcmjcnq</link>
    <thumbnail>https://image.tmdb.org/t/p/w1280/8RTPZ3i7sGWFg4rD6KFptkbniLJ.jpg</thumbnail>
    <fanart>https://image.tmdb.org/t/p/w1280/it2VjKfMblvKA9Jf9Qy4msgXvZw.jpg</fanart>
</item>
<item>
    <title>Kronk's New Groove</title>
    <meta>
        <imdb>tt0401398</imdb>
        <content>movie</content>
        <title>Kronk's New Groove</title>
        <year>2005</year>
    </meta>
    <link>https://uptostream.com/wr69bqyyh6r5</link>
    <thumbnail>https://image.tmdb.org/t/p/w1280/wytTF8brxjjWnzjfEq6EZBLdnDI.jpg</thumbnail>
    <fanart>https://image.tmdb.org/t/p/w1280/O2Bfpl52PwzUh2iJs2bXF4rewS.jpg</fanart>
</item>
<item>
    <title>Mickey, Donald, Goofy: The Three Musketeers</title>
    <meta>
        <imdb>tt0371823</imdb>
        <content>movie</content>
        <title>Mickey, Donald, Goofy: The Three Musketeers</title>
        <year>2004</year>
    </meta>
    <link>https://uptostream.com/9arn3surl4xr</link>
    <thumbnail>https://image.tmdb.org/t/p/w1280/uDvv54as7hLH7aWHwPyIVvoNb9K.jpg</thumbnail>
    <fanart>https://image.tmdb.org/t/p/w1280/8WodHELOg5guFPMIQf0M88IQhNE.jpg</fanart>
</item>
<item>
    <title>Mickey's Magical Christmas: Snowed in at the House of Mouse</title>
    <meta>
        <imdb>tt0300195</imdb>
        <content>movie</content>
        <title>Mickey's Magical Christmas: Snowed in at the House of Mouse</title>
        <year>2001</year>
    </meta>
    <link>https://uptostream.com/dxo0f2lhhm9f</link>
    <thumbnail>https://image.tmdb.org/t/p/w1280/3yIvYvNvarfvwc9YnC0ZbAHhfRK.jpg</thumbnail>
    <fanart>https://image.tmdb.org/t/p/w1280/zK2Z40YMpJXrdjtB87hLC4r07QS.jpg</fanart>
</item>
<item>
    <title>Buzz Lightyear of Star Command: The Adventure Begins</title>
    <meta>
        <imdb>tt0181196</imdb>
        <content>movie</content>
        <title>Buzz Lightyear of Star Command: The Adventure Begins</title>
        <year>2000</year>
    </meta>
    <link>https://uptostream.com/024etv1hex0y</link>
    <thumbnail>https://image.tmdb.org/t/p/w1280/3IXeVITL3FJ9CKpBK7lzULuw8Ts.jpg</thumbnail>
    <fanart>https://image.tmdb.org/t/p/w1280/evkhbIi0kLKrhkWhN05fZweWf0k.jpg</fanart>
</item>
<item>
    <title>Disney's Christmas Favourites</title>
    <meta>
        <imdb>tt1798141</imdb>
        <content>movie</content>
        <title>Disney's Christmas Favourites</title>
        <year>2005</year>
    </meta>
    <link>https://uptostream.com/vc5om9306r2l</link>
    <thumbnail>https://image.tmdb.org/t/p/w1280/sTXCxu6qFDgo77OGH5SDezbJ1vf.jpg</thumbnail>
    <fanart>https://image.tmdb.org/t/p/w1280/Al0iB9BSt9s7fY7TcCsZbt7V6l.jpg</fanart>
</item>
<item>
    <title>Valiant</title>
    <meta>
        <imdb>tt0361089</imdb>
        <content>movie</content>
        <title>Valiant</title>
        <year>2005</year>
    </meta>
    <link>https://uptostream.com/jxkowqop069m</link>
    <thumbnail>https://image.tmdb.org/t/p/w1280/chtAKvXb897I2Pn8HOkV4TC5Jzz.jpg</thumbnail>
    <fanart>https://image.tmdb.org/t/p/w1280/8s2iXxJQL8LMbNUrRad5auftoyN.jpg</fanart>
</item>
<item>
    <title>Bambi II</title>
    <meta>
        <imdb>tt0447854</imdb>
        <content>movie</content>
        <title>Bambi II</title>
        <year>2006</year>
    </meta>
    <link>https://uptostream.com/mh0qsu10hoip</link>
    <thumbnail>https://image.tmdb.org/t/p/w1280/vYqfG1SfpT4lJ5NXsNHY2otIfbt.jpg</thumbnail>
    <fanart>https://image.tmdb.org/t/p/w1280/ebug4NE8EV0f345KwbNNS3T3dRh.jpg</fanart>
</item>
<item>
    <title>Teacher's Pet</title>
    <meta>
        <imdb>tt0350194</imdb>
        <content>movie</content>
        <title>Teacher's Pet</title>
        <year>2004</year>
    </meta>
    <link>https://uptostream.com/e8bpswtryqgk</link>
    <thumbnail>https://image.tmdb.org/t/p/w1280/3IiwOT4QF4beOOdCLbJxdw7xzH1.jpg</thumbnail>
    <fanart>https://image.tmdb.org/t/p/w1280/eZk3COAbBcAi0HlKrDxUIxx3XPU.jpg</fanart>
</item>
<item>
    <title>Leroy & Stitch</title>
    <meta>
        <imdb>tt0486761</imdb>
        <content>movie</content>
        <title>Leroy & Stitch</title>
        <year>2006</year>
    </meta>
    <link>https://uptostream.com/642x5pe6vi8g</link>
    <thumbnail>https://image.tmdb.org/t/p/w1280/84ii0eIQy8wyzo5ZOSDbnoDtQ4O.jpg</thumbnail>
    <fanart>https://image.tmdb.org/t/p/w1280/fiM5VmEcUAxL6BWXpxWMshQ1imJ.jpg</fanart>
</item>
<item>
    <title>Cinderella III: A Twist in Time</title>
    <meta>
        <imdb>tt0465940</imdb>
        <content>movie</content>
        <title>Cinderella III: A Twist in Time</title>
        <year>2007</year>
    </meta>
    <link>https://uptostream.com/ut2n6xw7qkid</link>
    <thumbnail>https://image.tmdb.org/t/p/w1280/9QzKXbQfPp59iZ3rwnkKEAkPaXx.jpg</thumbnail>
    <fanart>https://image.tmdb.org/t/p/w1280/8IresDDceExrC67l7MxDOcITJTm.jpg</fanart>
</item>
<item>
    <title>Disney Princess Enchanted Tales: Follow Your Dreams</title>
    <meta>
        <imdb>none</imdb>
        <content>movie</content>
        <title>Disney Princess Enchanted Tales: Follow Your Dreams</title>
        <year>2007</year>
    </meta>
    <link>https://uptostream.com/m8w3hq8jx6z3</link>
    <thumbnail>https://image.tmdb.org/t/p/w1280/beAvTAhMQpTRxmlgGgpfg9F2rc1.jpg</thumbnail>
    <fanart>https://image.tmdb.org/t/p/w1280/7T6y6u1vUbZrCwQ9kFqH21CoAaB.jpg</fanart>
</item>
